<?xml version="1.0"?>
<arts version="1" format="ascii">
<GriddedField3>
<Vector name="Pressure" nelem="25">
1.0147100e+05
1.0000000e+05
9.7500000e+04
9.5000000e+04
9.2500000e+04
9.0000000e+04
8.7500000e+04
8.5000000e+04
8.0000000e+04
7.5000000e+04
7.0000000e+04
6.5000000e+04
6.0000000e+04
5.5000000e+04
5.0000000e+04
4.5000000e+04
4.0000000e+04
3.5000000e+04
3.0000000e+04
2.5000000e+04
2.0000000e+04
1.5000000e+04
1.0000000e+04
7.0000000e+03
5.0000000e+03
</Vector>
<Vector name="Latitude" nelem="1">
0.0000000e+00
</Vector>
<Vector name="Longitude" nelem="1">
0.0000000e+00
</Vector>
<Tensor3 ncols="1" nrows="1" npages="25">
2.0477578e-02
2.0317649e-02
2.0108076e-02
1.9772248e-02
2.0413465e-02
2.0515352e-02
1.9520473e-02
1.8081733e-02
1.5965605e-02
8.6812919e-03
8.5138603e-03
1.1645339e-02
9.9931517e-03
2.2733693e-03
3.3437556e-05
6.9240907e-04
2.7911253e-03
2.0211196e-03
8.7294447e-04
1.8799429e-04
6.9264255e-06
3.1294926e-07
2.6921244e-06
4.1720083e-06
5.1336405e-06
</Tensor3>
</GriddedField3>
</arts>
