<?xml version="1.0"?>
<arts version="1" format="ascii">
<GriddedField3>
<Vector name="Pressure" nelem="25">
1.0149000e+05
1.0000000e+05
9.7500000e+04
9.5000000e+04
9.2500000e+04
9.0000000e+04
8.7500000e+04
8.5000000e+04
8.0000000e+04
7.5000000e+04
7.0000000e+04
6.5000000e+04
6.0000000e+04
5.5000000e+04
5.0000000e+04
4.5000000e+04
4.0000000e+04
3.5000000e+04
3.0000000e+04
2.5000000e+04
2.0000000e+04
1.5000000e+04
1.0000000e+04
7.0000000e+03
5.0000000e+03
</Vector>
<Vector name="Latitude" nelem="1">
0.0000000e+00
</Vector>
<Vector name="Longitude" nelem="1">
0.0000000e+00
</Vector>
<Tensor3 ncols="1" nrows="1" npages="25">
2.9426500e+02
2.9275000e+02
2.9103900e+02
2.9033700e+02
2.9065200e+02
2.9052700e+02
2.9006500e+02
2.8993800e+02
2.8902700e+02
2.8615100e+02
2.8312500e+02
2.7981500e+02
2.7587500e+02
2.7202700e+02
2.7125000e+02
2.6633700e+02
2.5887500e+02
2.5221100e+02
2.4412500e+02
2.3275000e+02
2.1987500e+02
2.1084800e+02
2.0372400e+02
2.0650000e+02
2.1287500e+02
</Tensor3>
</GriddedField3>
</arts>
