<?xml version="1.0"?>
<arts version="1" format="ascii">
<GriddedField3>
<Vector name="Pressure" nelem="50">
1.0160000e+05
9.9600000e+04
9.7470000e+04
9.5400000e+04
9.3330000e+04
9.1300000e+04
8.9255000e+04
8.7225000e+04
8.5230000e+04
8.3170000e+04
8.1070000e+04
7.9020000e+04
7.6930000e+04
7.4935000e+04
7.2835000e+04
7.0795000e+04
6.8745000e+04
6.6685000e+04
6.4670000e+04
6.2630000e+04
6.0555000e+04
5.8485000e+04
5.6445000e+04
5.4360000e+04
5.2350000e+04
5.0280000e+04
4.8220000e+04
4.6170000e+04
4.4140000e+04
4.2080000e+04
4.0050000e+04
3.7990000e+04
3.5930000e+04
3.3870000e+04
3.1810000e+04
2.9750000e+04
2.7710000e+04
2.5650000e+04
2.3585000e+04
2.1550000e+04
1.9490000e+04
1.7450000e+04
1.5390000e+04
1.3325000e+04
1.1280000e+04
9.2400000e+03
7.1750000e+03
5.1250000e+03
3.0700000e+03
1.0200000e+03
</Vector>
<Vector name="Latitude" nelem="1">
0.0000000e+00
</Vector>
<Vector name="Longitude" nelem="1">
0.0000000e+00
</Vector>
<Tensor3 ncols="1" nrows="1" npages="50">
8.1000000e+01
8.2000000e+01
8.9000000e+01
9.6000000e+01
9.7000000e+01
8.7500000e+01
9.3500000e+01
8.0500000e+01
7.9000000e+01
7.5000000e+01
7.6000000e+01
6.7000000e+01
6.5000000e+01
6.4000000e+01
5.8000000e+01
5.4000000e+01
5.6500000e+01
5.4000000e+01
5.4000000e+01
4.9500000e+01
5.5000000e+01
5.5500000e+01
5.3000000e+01
6.1000000e+01
3.2000000e+01
2.8000000e+01
2.6500000e+01
3.9000000e+01
7.8000000e+01
8.7000000e+01
4.1000000e+01
4.1000000e+01
2.1000000e+01
3.4000000e+01
2.7000000e+01
9.0000000e+00
1.9000000e+01
3.0000000e+01
5.5000000e+01
3.2000000e+01
2.0000000e+01
4.5000000e+01
2.8000000e+01
1.9000000e+01
1.4000000e+01
1.2000000e+01
5.0000000e+00
1.0000000e+00
1.0000000e+00
1.0000000e+00
</Tensor3>
</GriddedField3>
</arts>
