<?xml version="1.0"?>
<arts version="1" format="ascii">
<GriddedField3>
<Vector name="Pressure" nelem="50">
1.0130000e+05
9.9295000e+04
9.7215000e+04
9.5115000e+04
9.3080000e+04
9.1105000e+04
8.9020000e+04
8.7000000e+04
8.4910000e+04
8.2870000e+04
8.0865000e+04
7.8820000e+04
7.6716667e+04
7.4670000e+04
7.2660000e+04
7.0620000e+04
6.8550000e+04
6.6510000e+04
6.4460000e+04
6.2370000e+04
6.0350000e+04
5.8325000e+04
5.6203333e+04
5.4210000e+04
5.2165000e+04
5.0115000e+04
4.8070000e+04
4.6025000e+04
4.3955000e+04
4.1895000e+04
3.9870000e+04
3.7780000e+04
3.5770000e+04
3.3710000e+04
3.1650000e+04
2.9610000e+04
2.7545000e+04
2.5520000e+04
2.3470000e+04
2.1425000e+04
1.9376667e+04
1.7310000e+04
1.5265000e+04
1.3210000e+04
1.1175000e+04
9.1150000e+03
7.0750000e+03
5.0300000e+03
2.9800000e+03
9.3000000e+02
</Vector>
<Vector name="Latitude" nelem="1">
0.0000000e+00
</Vector>
<Vector name="Longitude" nelem="1">
0.0000000e+00
</Vector>
<Tensor3 ncols="1" nrows="1" npages="50">
3.0297835e-02
2.8109945e-02
2.7223547e-02
2.4684481e-02
2.0189010e-02
1.7650123e-02
1.4383257e-02
1.4146632e-02
1.4959890e-02
1.2667410e-02
1.2630325e-02
1.3313425e-02
9.2852017e-03
6.1338600e-03
1.0783687e-02
1.0175654e-02
8.6574865e-03
5.1297704e-03
8.5187104e-03
6.6754417e-03
1.6043903e-03
1.8078819e-03
4.0656953e-03
4.2424242e-03
5.6922873e-03
4.8936209e-03
4.5822868e-03
4.3820770e-03
3.2271323e-03
1.6409766e-03
1.2806646e-03
6.5288307e-04
5.8830977e-04
4.0496431e-04
2.3312881e-04
2.1234601e-04
1.3216346e-04
8.2374025e-05
6.4954890e-05
6.8941813e-05
1.7825269e-05
7.7702765e-06
6.7622471e-06
5.5626956e-06
5.0690525e-06
3.5209180e-06
2.4377311e-06
2.7089392e-06
1.4549150e-05
2.6026267e-04
</Tensor3>
</GriddedField3>
</arts>
