<?xml version="1.0"?>
<arts version="1" format="ascii">
<GriddedField3>
<Vector name="Pressure" nelem="50">
1.0060000e+05
9.8610000e+04
9.6545000e+04
9.4500000e+04
9.2430000e+04
9.0410000e+04
8.8420000e+04
8.6370000e+04
8.4300000e+04
8.2330000e+04
8.0245000e+04
7.8200000e+04
7.6175000e+04
7.4115000e+04
7.2110000e+04
7.0050000e+04
6.8065000e+04
6.6040000e+04
6.4005000e+04
6.1920000e+04
5.9915000e+04
5.7885000e+04
5.5830000e+04
5.3790000e+04
5.1800000e+04
4.9740000e+04
4.7700000e+04
4.5670000e+04
4.3650000e+04
4.1605000e+04
3.9570000e+04
3.7520000e+04
3.5500000e+04
3.3440000e+04
3.1455000e+04
2.9390000e+04
2.7360000e+04
2.5335000e+04
2.3310000e+04
2.1250000e+04
1.9225000e+04
1.7205000e+04
1.5155000e+04
1.3125000e+04
1.1095000e+04
9.0550000e+03
7.0200000e+03
4.9900000e+03
2.9550000e+03
9.2000000e+02
</Vector>
<Vector name="Latitude" nelem="1">
0.0000000e+00
</Vector>
<Vector name="Longitude" nelem="1">
0.0000000e+00
</Vector>
<Tensor3 ncols="1" nrows="1" npages="50">
0.0000000e+00
1.8000000e+02
3.6000000e+02
5.5000000e+02
7.4000000e+02
9.3000000e+02
1.1200000e+03
1.3200000e+03
1.5300000e+03
1.7300000e+03
1.9500000e+03
2.1700000e+03
2.3900000e+03
2.6200000e+03
2.8500000e+03
3.0900000e+03
3.3300000e+03
3.5800000e+03
3.8400000e+03
4.1100000e+03
4.3800000e+03
4.6600000e+03
4.9500000e+03
5.2500000e+03
5.5500000e+03
5.8700000e+03
6.2000000e+03
6.5400000e+03
6.8900000e+03
7.2600000e+03
7.6400000e+03
8.0400000e+03
8.4500000e+03
8.8900000e+03
9.3400000e+03
9.8300000e+03
1.0340000e+04
1.0880000e+04
1.1450000e+04
1.2070000e+04
1.2720000e+04
1.3430000e+04
1.4220000e+04
1.5100000e+04
1.6120000e+04
1.7340000e+04
1.8860000e+04
2.0960000e+04
2.4310000e+04
3.1990000e+04
</Tensor3>
</GriddedField3>
</arts>
