<?xml version="1.0"?>
<arts version="1" format="ascii">
<GriddedField3>
<Vector name="Pressure" nelem="50">
1.0130000e+05
9.9256667e+04
9.7250000e+04
9.5115000e+04
9.3140000e+04
9.1080000e+04
8.9075000e+04
8.7000000e+04
8.4975000e+04
8.2910000e+04
8.0915000e+04
7.8835000e+04
7.6830000e+04
7.4785000e+04
7.2745000e+04
7.0635000e+04
6.8645000e+04
6.6605000e+04
6.4550000e+04
6.2520000e+04
6.0420000e+04
5.8380000e+04
5.6340000e+04
5.4355000e+04
5.2290000e+04
5.0250000e+04
4.8190000e+04
4.6150000e+04
4.4125000e+04
4.2045000e+04
4.0015000e+04
3.7965000e+04
3.5950000e+04
3.3915000e+04
3.1850000e+04
2.9820000e+04
2.7760000e+04
2.5720000e+04
2.3670000e+04
2.1640000e+04
1.9600000e+04
1.7550000e+04
1.5515000e+04
1.3475000e+04
1.1430000e+04
9.3800000e+03
7.3400000e+03
5.3000000e+03
3.2500000e+03
1.2100000e+03
</Vector>
<Vector name="Latitude" nelem="1">
0.0000000e+00
</Vector>
<Vector name="Longitude" nelem="1">
0.0000000e+00
</Vector>
<Tensor3 ncols="1" nrows="1" npages="50">
2.0687185e-02
2.0108626e-02
1.9786698e-02
1.9847256e-02
1.9602830e-02
1.9770714e-02
2.0225023e-02
2.0963910e-02
1.9711255e-02
1.7616167e-02
1.5499675e-02
1.4806405e-02
1.3848138e-02
1.5916803e-02
1.0532814e-02
6.5542185e-03
1.0151907e-02
1.3019231e-02
1.1954127e-02
1.1686602e-02
1.9633449e-03
5.9371744e-04
2.8177361e-04
1.3269818e-04
3.6361672e-04
1.0780074e-04
4.4423457e-04
3.4219552e-03
3.3334004e-03
1.9471988e-03
2.6816363e-03
7.1927638e-04
1.5012438e-03
9.8111536e-04
8.6874335e-04
8.8068007e-04
5.6712482e-04
1.6326537e-04
2.8590271e-04
2.3778078e-04
1.4969820e-04
6.4789828e-05
5.5915117e-06
4.4187447e-06
2.7421945e-06
2.8205812e-06
1.8968913e-06
3.0690843e-06
1.2563687e-05
1.0000142e-04
</Tensor3>
</GriddedField3>
</arts>
